deprecate/__init__.py
deprecate/deprecation.py
deprecate/utils.py
pyDeprecate-0.3.1.dist-info/LICENSE
pyDeprecate-0.3.1.dist-info/METADATA
pyDeprecate-0.3.1.dist-info/WHEEL
pyDeprecate-0.3.1.dist-info/top_level.txt
pyDeprecate-0.3.1.dist-info/RECORD
