Metadata-Version: 2.1
Name: pyDeprecate
Version: 0.3.1
Summary: Deprecation tooling
Home-page: https://borda.github.io/pyDeprecate
Author: Jiri Borovec
Author-email: jiri.borovec@fel.cvut.cz
License: MIT
Project-URL: Source Code, https://github.com/Borda/pyDeprecate
Keywords: python,development,deprecation
Platform: UNKNOWN
Classifier: Environment :: Console
Classifier: Natural Language :: English
Classifier: Development Status :: 3 - Alpha
Classifier: Intended Audience :: Developers
Classifier: Operating System :: OS Independent
Classifier: Programming Language :: Python :: 3
Classifier: Programming Language :: Python :: 3.6
Classifier: Programming Language :: Python :: 3.7
Classifier: Programming Language :: Python :: 3.8
Classifier: Programming Language :: Python :: 3.9
Requires-Python: >=3.6
License-File: LICENSE
